[
  {
    "id": "0x88c96ce1e6916bd5b0e7059e62b2dc8f07d86070bd440597c13a41b6b586fb1d",
    "loggedAt": "2026-03-25T22:09:59.153Z",
    "question": "Miami March 26: Will the highest temperature in Miami be between 82-83°F on March 26?",
    "city": "Miami",
    "date": "2026-03-26",
    "station": "KMIA",
    "forecastMethod": "forecast",
    "signalType": "CONSENSUS",
    "side": "NO",
    "polyProb": 43,
    "forecastProb": 21.8,
    "adjEdge": -22.1,
    "absEdge": 22.1,
    "annEdge": 4399.9,
    "observedMaxF": null,
    "observedMaxC": null,
    "localHour": null,
    "hoursToResolve": 44,
    "url": "https://polymarket.com/event/highest-temperature-in-miami-on-march-26-2026",
    "marketUrl": "https://polymarket.com/event/highest-temperature-in-miami-on-march-26-2026",
    "paperStake": 2,
    "paperSide": "NO",
    "paperEntry": 0.43,
    "resolved": true,
    "resolvedPrice": 1,
    "resolvedAt": "2026-03-29T10:01:55.315Z",
    "outcome": "LOSS",
    "paperPnl": -2
  },
  {
    "id": "0x245a9919bd5f5834b3440622a62a902c070dc0ea1589edda416eee52013ae3e7",
    "loggedAt": "2026-03-25T22:09:59.153Z",
    "question": "Atlanta March 26: Will the highest temperature in Atlanta be between 80-81°F on March 26?",
    "city": "Atlanta",
    "date": "2026-03-26",
    "station": "KATL",
    "forecastMethod": "forecast",
    "signalType": "CONSENSUS",
    "side": "NO",
    "polyProb": 39.5,
    "forecastProb": 21.4,
    "adjEdge": -18.9,
    "absEdge": 18.9,
    "annEdge": 3762.8,
    "observedMaxF": null,
    "observedMaxC": null,
    "localHour": null,
    "hoursToResolve": 44,
    "url": "https://polymarket.com/event/highest-temperature-in-atlanta-on-march-26-2026",
    "marketUrl": "https://polymarket.com/event/highest-temperature-in-atlanta-on-march-26-2026",
    "paperStake": 2,
    "paperSide": "NO",
    "paperEntry": 0.395,
    "resolved": true,
    "resolvedPrice": 0,
    "resolvedAt": "2026-03-29T10:01:57.600Z",
    "outcome": "WIN",
    "paperPnl": 1.31
  },
  {
    "id": "0x76e626b0ed23efa4ec7ba6e03e916e12951ddc3cd20afdc8fbee31feb6130a47",
    "loggedAt": "2026-03-25T22:09:59.153Z",
    "question": "Miami March 27: Will the highest temperature in Miami be between 82-83°F on March 27?",
    "city": "Miami",
    "date": "2026-03-27",
    "station": "KMIA",
    "forecastMethod": "forecast",
    "signalType": "CONSENSUS",
    "side": "NO",
    "polyProb": 39.5,
    "forecastProb": 21.6,
    "adjEdge": -18.7,
    "absEdge": 18.7,
    "annEdge": 2409,
    "observedMaxF": null,
    "observedMaxC": null,
    "localHour": null,
    "hoursToResolve": 68,
    "url": "https://polymarket.com/event/highest-temperature-in-miami-on-march-27-2026",
    "marketUrl": "https://polymarket.com/event/highest-temperature-in-miami-on-march-27-2026",
    "paperStake": 2,
    "paperSide": "NO",
    "paperEntry": 0.395,
    "resolved": true,
    "resolvedPrice": 1,
    "resolvedAt": "2026-03-29T10:01:58.249Z",
    "outcome": "LOSS",
    "paperPnl": -2
  },
  {
    "id": "0x7788d30df120abfcb3f2cde6ec6057bf746ea802aa62b5a7d6e2e275c150fe40",
    "loggedAt": "2026-03-25T22:09:59.153Z",
    "question": "Nyc March 27: Will the highest temperature in New York City be between 60-61°F on March 27?",
    "city": "Nyc",
    "date": "2026-03-27",
    "station": "KLGA",
    "forecastMethod": "forecast",
    "signalType": "CONSENSUS",
    "side": "NO",
    "polyProb": 35.5,
    "forecastProb": 18.7,
    "adjEdge": -17.5,
    "absEdge": 17.5,
    "annEdge": 2254.4,
    "observedMaxF": null,
    "observedMaxC": null,
    "localHour": null,
    "hoursToResolve": 68,
    "url": "https://polymarket.com/event/highest-temperature-in-nyc-on-march-27-2026",
    "marketUrl": "https://polymarket.com/event/highest-temperature-in-nyc-on-march-27-2026",
    "paperStake": 2,
    "paperSide": "NO",
    "paperEntry": 0.355,
    "resolved": true,
    "resolvedPrice": 0,
    "resolvedAt": "2026-03-29T10:01:58.584Z",
    "outcome": "WIN",
    "paperPnl": 1.1
  },
  {
    "id": "0x47cf273dce7993f3137b505cc706133ce040043940805a4062fddf8b4163a09d",
    "loggedAt": "2026-03-25T22:09:59.153Z",
    "question": "Chicago March 26: Will the highest temperature in Chicago be 59°F or below on March 26?",
    "city": "Chicago",
    "date": "2026-03-26",
    "station": "KORD",
    "forecastMethod": "forecast",
    "signalType": "CONSENSUS",
    "side": "NO",
    "polyProb": 23.9,
    "forecastProb": 9.7,
    "adjEdge": -14.7,
    "absEdge": 14.7,
    "annEdge": 2926.6,
    "observedMaxF": null,
    "observedMaxC": null,
    "localHour": null,
    "hoursToResolve": 44,
    "url": "https://polymarket.com/event/highest-temperature-in-chicago-on-march-26-2026",
    "marketUrl": "https://polymarket.com/event/highest-temperature-in-chicago-on-march-26-2026",
    "paperStake": 2,
    "paperSide": "NO",
    "paperEntry": 0.239,
    "resolved": true,
    "resolvedPrice": 0,
    "resolvedAt": "2026-03-29T10:01:59.264Z",
    "outcome": "WIN",
    "paperPnl": 0.63
  },
  {
    "id": "0xdc79479daba4fdd65392b9774540ea962f57c26e39cc9dca90795754cca6c8d2",
    "loggedAt": "2026-03-25T22:09:59.153Z",
    "question": "Dallas March 27: Will the highest temperature in Dallas be between 74-75°F on March 27?",
    "city": "Dallas",
    "date": "2026-03-27",
    "station": "KDAL",
    "forecastMethod": "forecast",
    "signalType": "CONSENSUS",
    "side": "NO",
    "polyProb": 17.5,
    "forecastProb": 3.7,
    "adjEdge": -14.2,
    "absEdge": 14.2,
    "annEdge": 1829.3,
    "observedMaxF": null,
    "observedMaxC": null,
    "localHour": null,
    "hoursToResolve": 68,
    "url": "https://polymarket.com/event/highest-temperature-in-dallas-on-march-27-2026",
    "marketUrl": "https://polymarket.com/event/highest-temperature-in-dallas-on-march-27-2026",
    "paperStake": 2,
    "paperSide": "NO",
    "paperEntry": 0.175,
    "resolved": true,
    "resolvedPrice": 1,
    "resolvedAt": "2026-03-29T10:02:00.236Z",
    "outcome": "LOSS",
    "paperPnl": -2
  },
  {
    "id": "0x5796772e8dd8f6f6d47a3f6b1e250a3e22a4912205dd697d9f1415879dc6c10e",
    "loggedAt": "2026-03-25T22:09:59.153Z",
    "question": "Atlanta March 27: Will the highest temperature in Atlanta be between 84-85°F on March 27?",
    "city": "Atlanta",
    "date": "2026-03-27",
    "station": "KATL",
    "forecastMethod": "forecast",
    "signalType": "CONSENSUS",
    "side": "NO",
    "polyProb": 34.5,
    "forecastProb": 21.9,
    "adjEdge": -13.3,
    "absEdge": 13.3,
    "annEdge": 1713.4,
    "observedMaxF": null,
    "observedMaxC": null,
    "localHour": null,
    "hoursToResolve": 68,
    "url": "https://polymarket.com/event/highest-temperature-in-atlanta-on-march-27-2026",
    "marketUrl": "https://polymarket.com/event/highest-temperature-in-atlanta-on-march-27-2026",
    "paperStake": 2,
    "paperSide": "NO",
    "paperEntry": 0.345,
    "resolved": true,
    "resolvedPrice": 0,
    "resolvedAt": "2026-03-29T10:02:00.882Z",
    "outcome": "WIN",
    "paperPnl": 1.05
  },
  {
    "id": "0x6c58d9fc1c216c1f9b77074d58cda081fb131a0527342be7236dcb86bc25c370",
    "loggedAt": "2026-03-25T22:09:59.153Z",
    "question": "Chicago March 27: Will the highest temperature in Chicago be between 44-45°F on March 27?",
    "city": "Chicago",
    "date": "2026-03-27",
    "station": "KORD",
    "forecastMethod": "forecast",
    "signalType": "CONSENSUS",
    "side": "YES",
    "polyProb": 8.5,
    "forecastProb": 20.5,
    "adjEdge": 11.8,
    "absEdge": 11.8,
    "annEdge": 1520.1,
    "observedMaxF": null,
    "observedMaxC": null,
    "localHour": null,
    "hoursToResolve": 68,
    "url": "https://polymarket.com/event/highest-temperature-in-chicago-on-march-27-2026",
    "marketUrl": "https://polymarket.com/event/highest-temperature-in-chicago-on-march-27-2026",
    "paperStake": 2,
    "paperSide": "YES",
    "paperEntry": 0.085,
    "resolved": true,
    "resolvedPrice": 1,
    "resolvedAt": "2026-03-29T10:02:02.173Z",
    "outcome": "WIN",
    "paperPnl": 21.53
  },
  {
    "id": "0xd075c85d68e4ad65372e4cea1a7198cd1a6ab88676f3224aa5eabc16010249e6",
    "loggedAt": "2026-03-25T22:09:59.153Z",
    "question": "Dallas March 27: Will the highest temperature in Dallas be between 84-85°F on March 27?",
    "city": "Dallas",
    "date": "2026-03-27",
    "station": "KDAL",
    "forecastMethod": "forecast",
    "signalType": "CONSENSUS",
    "side": "YES",
    "polyProb": 3.8,
    "forecastProb": 15.2,
    "adjEdge": 11.4,
    "absEdge": 11.4,
    "annEdge": 1468.6,
    "observedMaxF": null,
    "observedMaxC": null,
    "localHour": null,
    "hoursToResolve": 68,
    "url": "https://polymarket.com/event/highest-temperature-in-dallas-on-march-27-2026",
    "marketUrl": "https://polymarket.com/event/highest-temperature-in-dallas-on-march-27-2026",
    "paperStake": 2,
    "paperSide": "YES",
    "paperEntry": 0.038,
    "resolved": true,
    "resolvedPrice": 0,
    "resolvedAt": "2026-03-29T10:02:03.146Z",
    "outcome": "LOSS",
    "paperPnl": -2
  },
  {
    "id": "0xf39d939e07fb201329e25741c8f0ca61f7088e0401b606cd8d2fdb2dbe74a1c6",
    "loggedAt": "2026-03-25T22:09:59.153Z",
    "question": "Dallas March 26: Will the highest temperature in Dallas be between 86-87°F on March 26?",
    "city": "Dallas",
    "date": "2026-03-26",
    "station": "KDAL",
    "forecastMethod": "forecast",
    "signalType": "CONSENSUS",
    "side": "NO",
    "polyProb": 32.5,
    "forecastProb": 21.8,
    "adjEdge": -11.3,
    "absEdge": 11.3,
    "annEdge": 2249.7,
    "observedMaxF": null,
    "observedMaxC": null,
    "localHour": null,
    "hoursToResolve": 44,
    "url": "https://polymarket.com/event/highest-temperature-in-dallas-on-march-26-2026",
    "marketUrl": "https://polymarket.com/event/highest-temperature-in-dallas-on-march-26-2026",
    "paperStake": 2,
    "paperSide": "NO",
    "paperEntry": 0.325,
    "resolved": true,
    "resolvedPrice": 0,
    "resolvedAt": "2026-03-29T10:02:03.489Z",
    "outcome": "WIN",
    "paperPnl": 0.96
  },
  {
    "id": "0x8bc04fa104e3eb8a0c0ffee679e6166df89119dee0534534d8df567b4d610e3a",
    "loggedAt": "2026-03-25T22:09:59.153Z",
    "question": "Dallas March 27: Will the highest temperature in Dallas be between 82-83°F on March 27?",
    "city": "Dallas",
    "date": "2026-03-27",
    "station": "KDAL",
    "forecastMethod": "forecast",
    "signalType": "CONSENSUS",
    "side": "YES",
    "polyProb": 10,
    "forecastProb": 20.9,
    "adjEdge": 10.7,
    "absEdge": 10.7,
    "annEdge": 1378.4,
    "observedMaxF": null,
    "observedMaxC": null,
    "localHour": null,
    "hoursToResolve": 68,
    "url": "https://polymarket.com/event/highest-temperature-in-dallas-on-march-27-2026",
    "marketUrl": "https://polymarket.com/event/highest-temperature-in-dallas-on-march-27-2026",
    "paperStake": 2,
    "paperSide": "YES",
    "paperEntry": 0.1,
    "resolved": true,
    "resolvedPrice": 0,
    "resolvedAt": "2026-03-29T10:02:05.754Z",
    "outcome": "LOSS",
    "paperPnl": -2
  },
  {
    "id": "0x5f233e5562265ce15542974f005f1aa400fde9f663ba4dd2b94dbec93e35d787",
    "loggedAt": "2026-03-25T22:09:59.153Z",
    "question": "Dallas March 27: Will the highest temperature in Dallas be 86°F or higher on March 27?",
    "city": "Dallas",
    "date": "2026-03-27",
    "station": "KDAL",
    "forecastMethod": "forecast",
    "signalType": "CONSENSUS",
    "side": "YES",
    "polyProb": 2.1,
    "forecastProb": 12.6,
    "adjEdge": 10.5,
    "absEdge": 10.5,
    "annEdge": 1352.6,
    "observedMaxF": null,
    "observedMaxC": null,
    "localHour": null,
    "hoursToResolve": 68,
    "url": "https://polymarket.com/event/highest-temperature-in-dallas-on-march-27-2026",
    "marketUrl": "https://polymarket.com/event/highest-temperature-in-dallas-on-march-27-2026",
    "paperStake": 2,
    "paperSide": "YES",
    "paperEntry": 0.021,
    "resolved": true,
    "resolvedPrice": 0,
    "resolvedAt": "2026-03-29T10:02:06.399Z",
    "outcome": "LOSS",
    "paperPnl": -2
  },
  {
    "id": "0x92792999263a51d6fa5da7eef03cd688c653f80037021d2d5f19a6f998391f86",
    "loggedAt": "2026-03-25T22:09:59.153Z",
    "question": "Chicago March 27: Will the highest temperature in Chicago be between 38-39°F on March 27?",
    "city": "Chicago",
    "date": "2026-03-27",
    "station": "KORD",
    "forecastMethod": "forecast",
    "signalType": "CONSENSUS",
    "side": "NO",
    "polyProb": 19,
    "forecastProb": 9.6,
    "adjEdge": -9.8,
    "absEdge": 9.8,
    "annEdge": 1262.5,
    "observedMaxF": null,
    "observedMaxC": null,
    "localHour": null,
    "hoursToResolve": 68,
    "url": "https://polymarket.com/event/highest-temperature-in-chicago-on-march-27-2026",
    "marketUrl": "https://polymarket.com/event/highest-temperature-in-chicago-on-march-27-2026",
    "paperStake": 2,
    "paperSide": "NO",
    "paperEntry": 0.19,
    "resolved": true,
    "resolvedPrice": 0,
    "resolvedAt": "2026-03-29T10:02:06.735Z",
    "outcome": "WIN",
    "paperPnl": 0.47
  },
  {
    "id": "0x3140eb13e41f6fa7fb74a79dbcf534c1b794e8dc7f5af8825036fb9360587325",
    "loggedAt": "2026-03-25T22:09:59.153Z",
    "question": "Nyc March 27: Will the highest temperature in New York City be between 56-57°F on March 27?",
    "city": "Nyc",
    "date": "2026-03-27",
    "station": "KLGA",
    "forecastMethod": "forecast",
    "signalType": "CONSENSUS",
    "side": "YES",
    "polyProb": 9.5,
    "forecastProb": 19,
    "adjEdge": 9.3,
    "absEdge": 9.3,
    "annEdge": 1198.1,
    "observedMaxF": null,
    "observedMaxC": null,
    "localHour": null,
    "hoursToResolve": 68,
    "url": "https://polymarket.com/event/highest-temperature-in-nyc-on-march-27-2026",
    "marketUrl": "https://polymarket.com/event/highest-temperature-in-nyc-on-march-27-2026",
    "paperStake": 2,
    "paperSide": "YES",
    "paperEntry": 0.095,
    "resolved": true,
    "resolvedPrice": 0,
    "resolvedAt": "2026-03-29T10:02:07.064Z",
    "outcome": "LOSS",
    "paperPnl": -2
  },
  {
    "id": "0x38861256d9973e1479a0a3eea5139d1eb0a1fe48934518381a9f8928a8f3d068",
    "loggedAt": "2026-03-25T22:09:59.153Z",
    "question": "Chicago March 27: Will the highest temperature in Chicago be between 40-41°F on March 27?",
    "city": "Chicago",
    "date": "2026-03-27",
    "station": "KORD",
    "forecastMethod": "forecast",
    "signalType": "CONSENSUS",
    "side": "NO",
    "polyProb": 25.5,
    "forecastProb": 16.7,
    "adjEdge": -9.3,
    "absEdge": 9.3,
    "annEdge": 1198.1,
    "observedMaxF": null,
    "observedMaxC": null,
    "localHour": null,
    "hoursToResolve": 68,
    "url": "https://polymarket.com/event/highest-temperature-in-chicago-on-march-27-2026",
    "marketUrl": "https://polymarket.com/event/highest-temperature-in-chicago-on-march-27-2026",
    "paperStake": 2,
    "paperSide": "NO",
    "paperEntry": 0.255,
    "resolved": true,
    "resolvedPrice": 0,
    "resolvedAt": "2026-03-29T10:02:07.386Z",
    "outcome": "WIN",
    "paperPnl": 0.68
  },
  {
    "id": "0xdfd89a6eadcfd9fd6f29743ac728a10c4e88abe3cde6c75d1ea6eac84f7a2b27",
    "loggedAt": "2026-03-25T22:09:59.153Z",
    "question": "Nyc March 27: Will the highest temperature in New York City be between 54-55°F on March 27?",
    "city": "Nyc",
    "date": "2026-03-27",
    "station": "KLGA",
    "forecastMethod": "forecast",
    "signalType": "CONSENSUS",
    "side": "YES",
    "polyProb": 2.9,
    "forecastProb": 12.2,
    "adjEdge": 9.2,
    "absEdge": 9.2,
    "annEdge": 1185.2,
    "observedMaxF": null,
    "observedMaxC": null,
    "localHour": null,
    "hoursToResolve": 68,
    "url": "https://polymarket.com/event/highest-temperature-in-nyc-on-march-27-2026",
    "marketUrl": "https://polymarket.com/event/highest-temperature-in-nyc-on-march-27-2026",
    "paperStake": 2,
    "paperSide": "YES",
    "paperEntry": 0.028999999999999998,
    "resolved": true,
    "resolvedPrice": 0,
    "resolvedAt": "2026-03-29T10:02:07.709Z",
    "outcome": "LOSS",
    "paperPnl": -2
  },
  {
    "id": "0xb286c6a7fc2984182615ef69eb2bef15c1754e5b974d0684186e2533c93ef752",
    "loggedAt": "2026-03-25T22:09:59.153Z",
    "question": "Atlanta March 26: Will the highest temperature in Atlanta be between 76-77°F on March 26?",
    "city": "Atlanta",
    "date": "2026-03-26",
    "station": "KATL",
    "forecastMethod": "forecast",
    "signalType": "CONSENSUS",
    "side": "YES",
    "polyProb": 5.5,
    "forecastProb": 14.7,
    "adjEdge": 9.1,
    "absEdge": 9.1,
    "annEdge": 1811.7,
    "observedMaxF": null,
    "observedMaxC": null,
    "localHour": null,
    "hoursToResolve": 44,
    "url": "https://polymarket.com/event/highest-temperature-in-atlanta-on-march-26-2026",
    "marketUrl": "https://polymarket.com/event/highest-temperature-in-atlanta-on-march-26-2026",
    "paperStake": 2,
    "paperSide": "YES",
    "paperEntry": 0.055,
    "resolved": true,
    "resolvedPrice": 0,
    "resolvedAt": "2026-03-29T10:02:08.356Z",
    "outcome": "LOSS",
    "paperPnl": -2
  },
  {
    "id": "0xe1d5e18f65b1ff731ba955a00a2dea0d9e87631e74802ac5d26056cdd683efd2",
    "loggedAt": "2026-03-25T22:09:59.153Z",
    "question": "Dallas March 26: Will the highest temperature in Dallas be between 82-83°F on March 26?",
    "city": "Dallas",
    "date": "2026-03-26",
    "station": "KDAL",
    "forecastMethod": "forecast",
    "signalType": "CONSENSUS",
    "side": "YES",
    "polyProb": 2,
    "forecastProb": 11,
    "adjEdge": 9,
    "absEdge": 9,
    "annEdge": 1791.8,
    "observedMaxF": null,
    "observedMaxC": null,
    "localHour": null,
    "hoursToResolve": 44,
    "url": "https://polymarket.com/event/highest-temperature-in-dallas-on-march-26-2026",
    "marketUrl": "https://polymarket.com/event/highest-temperature-in-dallas-on-march-26-2026",
    "paperStake": 2,
    "paperSide": "YES",
    "paperEntry": 0.02,
    "resolved": true,
    "resolvedPrice": 0,
    "resolvedAt": "2026-03-29T10:02:08.677Z",
    "outcome": "LOSS",
    "paperPnl": -2
  },
  {
    "id": "0xf300c03d93bfcf057565a9d512a581443e2d3fbd27513fd5a1a5a9e554efb080",
    "loggedAt": "2026-03-25T22:09:59.153Z",
    "question": "Chicago March 26: Will the highest temperature in Chicago be between 62-63°F on March 26?",
    "city": "Chicago",
    "date": "2026-03-26",
    "station": "KORD",
    "forecastMethod": "forecast",
    "signalType": "CONSENSUS",
    "side": "YES",
    "polyProb": 11,
    "forecastProb": 19.7,
    "adjEdge": 8.5,
    "absEdge": 8.5,
    "annEdge": 1692.3,
    "observedMaxF": null,
    "observedMaxC": null,
    "localHour": null,
    "hoursToResolve": 44,
    "url": "https://polymarket.com/event/highest-temperature-in-chicago-on-march-26-2026",
    "marketUrl": "https://polymarket.com/event/highest-temperature-in-chicago-on-march-26-2026",
    "paperStake": 2,
    "paperSide": "YES",
    "paperEntry": 0.11,
    "resolved": true,
    "resolvedPrice": 0,
    "resolvedAt": "2026-03-29T10:02:09.975Z",
    "outcome": "LOSS",
    "paperPnl": -2
  },
  {
    "id": "0x05487a9ddfd0021da26da783c591d068eb9f19872464c5aa74a3cad4d4f003e1",
    "loggedAt": "2026-03-25T22:09:59.153Z",
    "question": "Miami March 26: Will the highest temperature in Miami be between 78-79°F on March 26?",
    "city": "Miami",
    "date": "2026-03-26",
    "station": "KMIA",
    "forecastMethod": "forecast",
    "signalType": "CONSENSUS",
    "side": "YES",
    "polyProb": 4.6,
    "forecastProb": 13.1,
    "adjEdge": 8.4,
    "absEdge": 8.4,
    "annEdge": 1672.4,
    "observedMaxF": null,
    "observedMaxC": null,
    "localHour": null,
    "hoursToResolve": 44,
    "url": "https://polymarket.com/event/highest-temperature-in-miami-on-march-26-2026",
    "marketUrl": "https://polymarket.com/event/highest-temperature-in-miami-on-march-26-2026",
    "paperStake": 2,
    "paperSide": "YES",
    "paperEntry": 0.046,
    "resolved": true,
    "resolvedPrice": 0,
    "resolvedAt": "2026-03-29T10:02:10.299Z",
    "outcome": "LOSS",
    "paperPnl": -2
  },
  {
    "id": "0x6914e46fcfa8989a0d9896c009efd650fa399bc236f85f7d70308837c305dbaf",
    "loggedAt": "2026-03-25T22:09:59.153Z",
    "question": "Miami March 27: Will the highest temperature in Miami be between 78-79°F on March 27?",
    "city": "Miami",
    "date": "2026-03-27",
    "station": "KMIA",
    "forecastMethod": "forecast",
    "signalType": "CONSENSUS",
    "side": "YES",
    "polyProb": 6,
    "forecastProb": 14.1,
    "adjEdge": 8,
    "absEdge": 8,
    "annEdge": 1030.6,
    "observedMaxF": null,
    "observedMaxC": null,
    "localHour": null,
    "hoursToResolve": 68,
    "url": "https://polymarket.com/event/highest-temperature-in-miami-on-march-27-2026",
    "marketUrl": "https://polymarket.com/event/highest-temperature-in-miami-on-march-27-2026",
    "paperStake": 2,
    "paperSide": "YES",
    "paperEntry": 0.06,
    "resolved": true,
    "resolvedPrice": 0,
    "resolvedAt": "2026-03-29T10:02:10.646Z",
    "outcome": "LOSS",
    "paperPnl": -2
  },
  {
    "id": "0x29be92b1f8d8846469e78eda4d9e64055c167f478d4362395f950b86fa66f25a",
    "loggedAt": "2026-03-25T22:09:59.153Z",
    "question": "Miami March 27: Will the highest temperature in Miami be between 84-85°F on March 27?",
    "city": "Miami",
    "date": "2026-03-27",
    "station": "KMIA",
    "forecastMethod": "forecast",
    "signalType": "CONSENSUS",
    "side": "YES",
    "polyProb": 9,
    "forecastProb": 17.1,
    "adjEdge": 7.9,
    "absEdge": 7.9,
    "annEdge": 1017.7,
    "observedMaxF": null,
    "observedMaxC": null,
    "localHour": null,
    "hoursToResolve": 68,
    "url": "https://polymarket.com/event/highest-temperature-in-miami-on-march-27-2026",
    "marketUrl": "https://polymarket.com/event/highest-temperature-in-miami-on-march-27-2026",
    "paperStake": 2,
    "paperSide": "YES",
    "paperEntry": 0.09,
    "resolved": true,
    "resolvedPrice": 0,
    "resolvedAt": "2026-03-29T10:02:10.962Z",
    "outcome": "LOSS",
    "paperPnl": -2
  },
  {
    "id": "0x54f9dc6dbe7716fa4ac2cead6afab9f4e844a6d8eba75bda1c7f85d8d0c7627b",
    "loggedAt": "2026-03-25T22:09:59.153Z",
    "question": "Miami March 26: Will the highest temperature in Miami be between 86-87°F on March 26?",
    "city": "Miami",
    "date": "2026-03-26",
    "station": "KMIA",
    "forecastMethod": "forecast",
    "signalType": "CONSENSUS",
    "side": "YES",
    "polyProb": 2.9,
    "forecastProb": 10.9,
    "adjEdge": 7.9,
    "absEdge": 7.9,
    "annEdge": 1572.8,
    "observedMaxF": null,
    "observedMaxC": null,
    "localHour": null,
    "hoursToResolve": 44,
    "url": "https://polymarket.com/event/highest-temperature-in-miami-on-march-26-2026",
    "marketUrl": "https://polymarket.com/event/highest-temperature-in-miami-on-march-26-2026",
    "paperStake": 2,
    "paperSide": "YES",
    "paperEntry": 0.028999999999999998,
    "resolved": true,
    "resolvedPrice": 0,
    "resolvedAt": "2026-03-29T10:02:11.286Z",
    "outcome": "LOSS",
    "paperPnl": -2
  },
  {
    "id": "0xbbf90eed889e0b6ed8219ce5af168e50f17ef390035ca2263ef278ee7fa90810",
    "loggedAt": "2026-03-25T22:09:59.153Z",
    "question": "Miami March 26: Will the highest temperature in Miami be between 80-81°F on March 26?",
    "city": "Miami",
    "date": "2026-03-26",
    "station": "KMIA",
    "forecastMethod": "forecast",
    "signalType": "CONSENSUS",
    "side": "NO",
    "polyProb": 26.5,
    "forecastProb": 19.6,
    "adjEdge": -7.4,
    "absEdge": 7.4,
    "annEdge": 1473.3,
    "observedMaxF": null,
    "observedMaxC": null,
    "localHour": null,
    "hoursToResolve": 44,
    "url": "https://polymarket.com/event/highest-temperature-in-miami-on-march-26-2026",
    "marketUrl": "https://polymarket.com/event/highest-temperature-in-miami-on-march-26-2026",
    "paperStake": 2,
    "paperSide": "NO",
    "paperEntry": 0.265,
    "resolved": true,
    "resolvedPrice": 0,
    "resolvedAt": "2026-03-29T10:02:12.579Z",
    "outcome": "WIN",
    "paperPnl": 0.72
  },
  {
    "id": "0x933de9abdff6bc79f99e85223f30dcfb3633beba86a981e9669ab8db3bfeaa46",
    "loggedAt": "2026-03-25T22:09:59.153Z",
    "question": "Miami March 27: Will the highest temperature in Miami be between 80-81°F on March 27?",
    "city": "Miami",
    "date": "2026-03-27",
    "station": "KMIA",
    "forecastMethod": "forecast",
    "signalType": "CONSENSUS",
    "side": "NO",
    "polyProb": 27,
    "forecastProb": 20.3,
    "adjEdge": -7.2,
    "absEdge": 7.2,
    "annEdge": 927.5,
    "observedMaxF": null,
    "observedMaxC": null,
    "localHour": null,
    "hoursToResolve": 68,
    "url": "https://polymarket.com/event/highest-temperature-in-miami-on-march-27-2026",
    "marketUrl": "https://polymarket.com/event/highest-temperature-in-miami-on-march-27-2026",
    "paperStake": 2,
    "paperSide": "NO",
    "paperEntry": 0.27,
    "resolved": true,
    "resolvedPrice": 0,
    "resolvedAt": "2026-03-29T10:02:12.904Z",
    "outcome": "WIN",
    "paperPnl": 0.74
  },
  {
    "id": "0xe43e9dc83c72471606c11e1fddc20042f5b9e015803cf0aebdc3adabc776a7ad",
    "loggedAt": "2026-03-25T22:09:59.153Z",
    "question": "Dallas March 27: Will the highest temperature in Dallas be between 76-77°F on March 27?",
    "city": "Dallas",
    "date": "2026-03-27",
    "station": "KDAL",
    "forecastMethod": "forecast",
    "signalType": "CONSENSUS",
    "side": "NO",
    "polyProb": 15.5,
    "forecastProb": 8.9,
    "adjEdge": -6.9,
    "absEdge": 6.9,
    "annEdge": 888.9,
    "observedMaxF": null,
    "observedMaxC": null,
    "localHour": null,
    "hoursToResolve": 68,
    "url": "https://polymarket.com/event/highest-temperature-in-dallas-on-march-27-2026",
    "marketUrl": "https://polymarket.com/event/highest-temperature-in-dallas-on-march-27-2026",
    "paperStake": 2,
    "paperSide": "NO",
    "paperEntry": 0.155,
    "resolved": true,
    "resolvedPrice": 0,
    "resolvedAt": "2026-03-29T10:02:13.226Z",
    "outcome": "WIN",
    "paperPnl": 0.37
  },
  {
    "id": "0xa9155718f53ee532833d29a3fcd4586d6ef5e431caf3c89ab5ebc82aa85a8165",
    "loggedAt": "2026-03-25T22:09:59.153Z",
    "question": "Chicago March 27: Will the highest temperature in Chicago be between 46-47°F on March 27?",
    "city": "Chicago",
    "date": "2026-03-27",
    "station": "KORD",
    "forecastMethod": "forecast",
    "signalType": "CONSENSUS",
    "side": "YES",
    "polyProb": 7.5,
    "forecastProb": 14.4,
    "adjEdge": 6.8,
    "absEdge": 6.8,
    "annEdge": 876,
    "observedMaxF": null,
    "observedMaxC": null,
    "localHour": null,
    "hoursToResolve": 68,
    "url": "https://polymarket.com/event/highest-temperature-in-chicago-on-march-27-2026",
    "marketUrl": "https://polymarket.com/event/highest-temperature-in-chicago-on-march-27-2026",
    "paperStake": 2,
    "paperSide": "YES",
    "paperEntry": 0.075,
    "resolved": true,
    "resolvedPrice": 0,
    "resolvedAt": "2026-03-29T10:02:13.871Z",
    "outcome": "LOSS",
    "paperPnl": -2
  },
  {
    "id": "0xe29ecf75b9000501f0222fab686d7872e0a6ca0989ab55d05652136c341ed378",
    "loggedAt": "2026-03-25T22:09:59.153Z",
    "question": "Dallas March 27: Will the highest temperature in Dallas be between 80-81°F on March 27?",
    "city": "Dallas",
    "date": "2026-03-27",
    "station": "KDAL",
    "forecastMethod": "forecast",
    "signalType": "CONSENSUS",
    "side": "NO",
    "polyProb": 27.5,
    "forecastProb": 21.3,
    "adjEdge": -6.8,
    "absEdge": 6.8,
    "annEdge": 876,
    "observedMaxF": null,
    "observedMaxC": null,
    "localHour": null,
    "hoursToResolve": 68,
    "url": "https://polymarket.com/event/highest-temperature-in-dallas-on-march-27-2026",
    "marketUrl": "https://polymarket.com/event/highest-temperature-in-dallas-on-march-27-2026",
    "paperStake": 2,
    "paperSide": "NO",
    "paperEntry": 0.275,
    "resolved": true,
    "resolvedPrice": 0,
    "resolvedAt": "2026-03-29T10:02:14.201Z",
    "outcome": "WIN",
    "paperPnl": 0.76
  },
  {
    "id": "0x0abf938f53d98c17e269ecb29606699129314e74cbd65c3ef9a0e6a6fb519896",
    "loggedAt": "2026-03-25T22:09:59.153Z",
    "question": "Atlanta March 27: Will the highest temperature in Atlanta be between 82-83°F on March 27?",
    "city": "Atlanta",
    "date": "2026-03-27",
    "station": "KATL",
    "forecastMethod": "forecast",
    "signalType": "CONSENSUS",
    "side": "NO",
    "polyProb": 24.5,
    "forecastProb": 18.3,
    "adjEdge": -6.7,
    "absEdge": 6.7,
    "annEdge": 863.1,
    "observedMaxF": null,
    "observedMaxC": null,
    "localHour": null,
    "hoursToResolve": 68,
    "url": "https://polymarket.com/event/highest-temperature-in-atlanta-on-march-27-2026",
    "marketUrl": "https://polymarket.com/event/highest-temperature-in-atlanta-on-march-27-2026",
    "paperStake": 2,
    "paperSide": "NO",
    "paperEntry": 0.245,
    "resolved": true,
    "resolvedPrice": 1,
    "resolvedAt": "2026-03-29T10:02:14.520Z",
    "outcome": "LOSS",
    "paperPnl": -2
  },
  {
    "id": "0x2900da45a610976a1a1af60ca53890c94f444acf81a4c3c0fc8fa62273b38530",
    "loggedAt": "2026-03-25T22:09:59.153Z",
    "question": "Atlanta March 27: Will the highest temperature in Atlanta be between 88-89°F on March 27?",
    "city": "Atlanta",
    "date": "2026-03-27",
    "station": "KATL",
    "forecastMethod": "forecast",
    "signalType": "CONSENSUS",
    "side": "YES",
    "polyProb": 6.5,
    "forecastProb": 12.7,
    "adjEdge": 6.1,
    "absEdge": 6.1,
    "annEdge": 785.8,
    "observedMaxF": null,
    "observedMaxC": null,
    "localHour": null,
    "hoursToResolve": 68,
    "url": "https://polymarket.com/event/highest-temperature-in-atlanta-on-march-27-2026",
    "marketUrl": "https://polymarket.com/event/highest-temperature-in-atlanta-on-march-27-2026",
    "paperStake": 2,
    "paperSide": "YES",
    "paperEntry": 0.065,
    "resolved": true,
    "resolvedPrice": 0,
    "resolvedAt": "2026-03-29T10:02:15.812Z",
    "outcome": "LOSS",
    "paperPnl": -2
  },
  {
    "id": "0x1789f888009aacf3964deb45f98c4e02d225cf8a967116008b1d2678960feb24",
    "loggedAt": "2026-03-25T22:09:59.153Z",
    "question": "Dallas March 27: Will the highest temperature in Dallas be between 72-73°F on March 27?",
    "city": "Dallas",
    "date": "2026-03-27",
    "station": "KDAL",
    "forecastMethod": "forecast",
    "signalType": "CONSENSUS",
    "side": "NO",
    "polyProb": 7,
    "forecastProb": 1.1,
    "adjEdge": -6,
    "absEdge": 6,
    "annEdge": 772.9,
    "observedMaxF": null,
    "observedMaxC": null,
    "localHour": null,
    "hoursToResolve": 68,
    "url": "https://polymarket.com/event/highest-temperature-in-dallas-on-march-27-2026",
    "marketUrl": "https://polymarket.com/event/highest-temperature-in-dallas-on-march-27-2026",
    "paperStake": 2,
    "paperSide": "NO",
    "paperEntry": 0.07,
    "resolved": true,
    "resolvedPrice": 0,
    "resolvedAt": "2026-03-29T10:02:16.135Z",
    "outcome": "WIN",
    "paperPnl": 0.15
  },
  {
    "id": "0x02c11389cec5cf2a318116a26ffe47a98f73eaba7f8e9ebf21325efb53b2591b",
    "loggedAt": "2026-03-25T22:09:59.153Z",
    "question": "Atlanta March 26: Will the highest temperature in Atlanta be between 74-75°F on March 26?",
    "city": "Atlanta",
    "date": "2026-03-26",
    "station": "KATL",
    "forecastMethod": "forecast",
    "signalType": "CONSENSUS",
    "side": "YES",
    "polyProb": 1.8,
    "forecastProb": 7.7,
    "adjEdge": 5.9,
    "absEdge": 5.9,
    "annEdge": 1174.6,
    "observedMaxF": null,
    "observedMaxC": null,
    "localHour": null,
    "hoursToResolve": 44,
    "url": "https://polymarket.com/event/highest-temperature-in-atlanta-on-march-26-2026",
    "marketUrl": "https://polymarket.com/event/highest-temperature-in-atlanta-on-march-26-2026",
    "paperStake": 2,
    "paperSide": "YES",
    "paperEntry": 0.018000000000000002,
    "resolved": true,
    "resolvedPrice": 0,
    "resolvedAt": "2026-03-29T10:02:16.458Z",
    "outcome": "LOSS",
    "paperPnl": -2
  },
  {
    "id": "0xa3996983e1c1007ff5f15ed04da3bdf7871b32a5af8209c48ff60476109e3073",
    "loggedAt": "2026-03-25T22:09:59.153Z",
    "question": "Dallas March 26: Will the highest temperature in Dallas be between 88-89°F on March 26?",
    "city": "Dallas",
    "date": "2026-03-26",
    "station": "KDAL",
    "forecastMethod": "forecast",
    "signalType": "CONSENSUS",
    "side": "NO",
    "polyProb": 25,
    "forecastProb": 19.6,
    "adjEdge": -5.9,
    "absEdge": 5.9,
    "annEdge": 1174.6,
    "observedMaxF": null,
    "observedMaxC": null,
    "localHour": null,
    "hoursToResolve": 44,
    "url": "https://polymarket.com/event/highest-temperature-in-dallas-on-march-26-2026",
    "marketUrl": "https://polymarket.com/event/highest-temperature-in-dallas-on-march-26-2026",
    "paperStake": 2,
    "paperSide": "NO",
    "paperEntry": 0.25,
    "resolved": true,
    "resolvedPrice": 0,
    "resolvedAt": "2026-03-29T10:02:16.783Z",
    "outcome": "WIN",
    "paperPnl": 0.67
  },
  {
    "id": "0xc9ebbc9c110550c6d23a5be9f15d0e6d397160599e7d33e836dacefce34525f7",
    "loggedAt": "2026-03-25T22:09:59.153Z",
    "question": "Atlanta March 27: Will the highest temperature in Atlanta be between 80-81°F on March 27?",
    "city": "Atlanta",
    "date": "2026-03-27",
    "station": "KATL",
    "forecastMethod": "forecast",
    "signalType": "CONSENSUS",
    "side": "YES",
    "polyProb": 5.5,
    "forecastProb": 11.3,
    "adjEdge": 5.7,
    "absEdge": 5.7,
    "annEdge": 734.3,
    "observedMaxF": null,
    "observedMaxC": null,
    "localHour": null,
    "hoursToResolve": 68,
    "url": "https://polymarket.com/event/highest-temperature-in-atlanta-on-march-27-2026",
    "marketUrl": "https://polymarket.com/event/highest-temperature-in-atlanta-on-march-27-2026",
    "paperStake": 2,
    "paperSide": "YES",
    "paperEntry": 0.055,
    "resolved": true,
    "resolvedPrice": 0,
    "resolvedAt": "2026-03-29T10:02:17.106Z",
    "outcome": "LOSS",
    "paperPnl": -2
  },
  {
    "id": "0x234f0a9cfc1d79a94f3f1f1652a5ebc8cd58694a869643ff13f77d1ff6cc908e",
    "loggedAt": "2026-03-25T22:09:59.153Z",
    "question": "Nyc March 27: Will the highest temperature in New York City be between 58-59°F on March 27?",
    "city": "Nyc",
    "date": "2026-03-27",
    "station": "KLGA",
    "forecastMethod": "forecast",
    "signalType": "CONSENSUS",
    "side": "NO",
    "polyProb": 26.5,
    "forecastProb": 21.9,
    "adjEdge": -5.1,
    "absEdge": 5.1,
    "annEdge": 657,
    "observedMaxF": null,
    "observedMaxC": null,
    "localHour": null,
    "hoursToResolve": 68,
    "url": "https://polymarket.com/event/highest-temperature-in-nyc-on-march-27-2026",
    "marketUrl": "https://polymarket.com/event/highest-temperature-in-nyc-on-march-27-2026",
    "paperStake": 2,
    "paperSide": "NO",
    "paperEntry": 0.265,
    "resolved": true,
    "resolvedPrice": 0,
    "resolvedAt": "2026-03-29T10:02:17.756Z",
    "outcome": "WIN",
    "paperPnl": 0.72
  },
  {
    "id": "0x0f27588ae53dda178d9e7ed57fe73c1d423692a3fb3ef3f69244bbc2d66e2511",
    "loggedAt": "2026-03-25T22:09:59.153Z",
    "question": "Miami March 27: Will the highest temperature in Miami be between 76-77°F on March 27?",
    "city": "Miami",
    "date": "2026-03-27",
    "station": "KMIA",
    "forecastMethod": "forecast",
    "signalType": "CONSENSUS",
    "side": "YES",
    "polyProb": 2.2,
    "forecastProb": 7.2,
    "adjEdge": 5,
    "absEdge": 5,
    "annEdge": 644.1,
    "observedMaxF": null,
    "observedMaxC": null,
    "localHour": null,
    "hoursToResolve": 68,
    "url": "https://polymarket.com/event/highest-temperature-in-miami-on-march-27-2026",
    "marketUrl": "https://polymarket.com/event/highest-temperature-in-miami-on-march-27-2026",
    "paperStake": 2,
    "paperSide": "YES",
    "paperEntry": 0.022000000000000002,
    "resolved": true,
    "resolvedPrice": 0,
    "resolvedAt": "2026-03-29T10:02:18.101Z",
    "outcome": "LOSS",
    "paperPnl": -2
  }
]